shortener.py
shortener/__init__.py
shortener/shortener.py
urltool/__init__.py
urltool/shortener.py
urltool-1.0.2.dist-info/METADATA
urltool-1.0.2.dist-info/WHEEL
urltool-1.0.2.dist-info/top_level.txt
urltool-1.0.2.dist-info/RECORD
